ccad/__init__.py
ccad/app_constants.py
ccad/assembly.py
ccad/connector.py
ccad/constants.py
ccad/double_filter_reactor.py
ccad/double_siphon.py
ccad/exceptions.py
ccad/filter_like_reactors.py
ccad/filter_reactor.py
ccad/floating_filter_reactor.py
ccad/flow_reactor.py
ccad/in_out.py
ccad/jasmine.py
ccad/log.py
ccad/misc.py
ccad/object.py
ccad/pipe.py
ccad/reactor.py
ccad/siphon.py
ccad/top_in.py
ccad/tops_placement.py
ccad/tube_connector.py
ccad/bin/win/openscad.com
ccad/bin/win/openscad.exe
tests/__init__.py
tests/test_assembly.py
tests/test_double_siphon.py
tests/test_filter_reactor.py
tests/test_floating_filter_reactor.py
tests/test_reactor.py
tests/test_siphon.py
tests/test_top_placement.py
tests/test_tube_connector.py
ccad-2.0.dist-info/LICENSE.txt
ccad-2.0.dist-info/METADATA
ccad-2.0.dist-info/WHEEL
ccad-2.0.dist-info/top_level.txt
ccad-2.0.dist-info/RECORD
