Metadata-Version: 2.1
Name: ccad
Version: 2.0
Summary: Python library to render Reactionware cartridges
Home-page: https://github.com/croningroup/ccad
Author: Cronin Group
Author-email: croningp.pypi@gmail.com
License: UNKNOWN
Platform: UNKNOWN
Classifier: Programming Language :: Python :: 3
Classifier: License :: OSI Approved :: GNU Affero General Public License v3 or later (AGPLv3+)
Classifier: Operating System :: OS Independent
Requires-Python: >=3.6
Requires-Dist: numpy
Requires-Dist: scipy
Requires-Dist: solidpython
